src/doc/background.md
src/doc/clusters.md
src/doc/editing-ontologies.md
src/doc/example-narration.md
src/doc/example-process.md
src/doc/rdf-and-types.md
src/doc/usd-framing.md
src/ontologies/ontologies.md
src/ontologies/clusters/clusters.md
src/ontologies/clusters/assembly/assembly.md
src/ontologies/clusters/assembly/fera-v001-assembly-cluster.svg
src/ontologies/clusters/assembly/feraAssemblySchema.ts
src/ontologies/clusters/base/base.md
src/ontologies/clusters/base/baseSchema.ts
src/ontologies/clusters/base/fera-v001-base-cluster.svg
src/ontologies/clusters/bdd/all-v022-bdd-cluster.svg
src/ontologies/clusters/bdd/bdd.md
src/ontologies/clusters/bdd/bddSchema.ts
src/ontologies/clusters/core/core.md
src/ontologies/clusters/core/coreSchema.ts
src/ontologies/clusters/core/facilityCobot-v022-core-cluster.svg
src/ontologies/clusters/digitech/digitech-v022-digitech-cluster-scoped.svg
src/ontologies/clusters/digitech/digitech-v022-digitech-cluster.svg
src/ontologies/clusters/digitech/digitech.md
src/ontologies/clusters/digitech/digitechSchema.ts
src/ontologies/clusters/dul/dul.md
src/ontologies/clusters/dul/dulSchema.ts
src/ontologies/clusters/dul/fera-v001-dul-cluster.svg
src/ontologies/clusters/fc/facilityCobot-v022-fc-cluster.svg
src/ontologies/clusters/fc/fc.md
src/ontologies/clusters/fc/fcSchema.ts
src/ontologies/clusters/fera/fera-v001-fera-cluster-scoped.svg
src/ontologies/clusters/fera/fera-v001-fera-cluster.svg
src/ontologies/clusters/fera/fera.md
src/ontologies/clusters/fera/feraSchema.ts
src/ontologies/clusters/i4/digitech-v022-i4-cluster-unscoped.svg
src/ontologies/clusters/i4/digitech-v022-i4-cluster.svg
src/ontologies/clusters/i4/i4.md
src/ontologies/clusters/i4/i4Schema.ts
src/ontologies/clusters/metric/all-v022-metric-cluster.svg
src/ontologies/clusters/metric/metric.md
src/ontologies/clusters/metric/metricSchema.ts
src/ontologies/clusters/otlp/otlp.md
src/ontologies/clusters/otlp/otlp.svg
src/ontologies/clusters/plant/all-v022-plant-cluster.svg
semantic_fera-0.0.2.dist-info/METADATA
semantic_fera-0.0.2.dist-info/WHEEL
semantic_fera-0.0.2.dist-info/licenses/LICENSE
semantic_fera-0.0.2.dist-info/licenses/NOTICE
semantic_fera-0.0.2.dist-info/RECORD
