Metadata-Version: 2.4
Name: semantic-fera
Version: 0.0.2
Summary: FERA ontologies, type definitions, type constructors, configurations 
Project-URL: Homepage, https://source.coderefinery.org:fera/semantic-fera
Project-URL: Issues, https://source.coderefinery.org:fera/semantic-fera/-/issues
Author-email: William A Coolidge <wac@mmmi.sdu.dk>
License-File: LICENSE
License-File: NOTICE
Requires-Dist: behave==1.2.6
Requires-Dist: future==0.18.2
Requires-Dist: paho-mqtt==2.1.0
Requires-Dist: pydantic-core==2.27.2
Requires-Dist: pydantic==2.10.4
Requires-Dist: pymonad==2.4.0
Requires-Dist: pyrsistent==0.20.0
Requires-Dist: semantic-api>=0.0.18
Requires-Dist: typing-extensions==4.12.2
Requires-Dist: typing==3.7.4.3
Requires-Dist: urllib3==1.26.5
